[
    {
        "Từ vựng": "inform",
        "Phiên âm": "/ɪnˈfɔːm/",
        "Loại từ": "v",
        "Ý nghĩa": "thông báo, cho biết",
        "Cách nhớ nhanh": "In phone báo tin – inform"
    },
    {
        "Từ vựng": "infuriate",
        "Phiên âm": "/ɪnˈfjʊərieɪt/",
        "Loại từ": "v",
        "Ý nghĩa": "làm điên tiết",
        "Cách nhớ nhanh": "In phiêu rồ lên – infuriate"
    },
    {
        "Từ vựng": "ingenious",
        "Phiên âm": "/ɪnˈdʒiːniəs/",
        "Loại từ": "adj",
        "Ý nghĩa": "tài tình, khéo léo",
        "Cách nhớ nhanh": "In như nghệ sĩ – sáng tạo"
    },
    {
        "Từ vựng": "inhabitant",
        "Phiên âm": "/ɪnˈhæbɪtənt/",
        "Loại từ": "n",
        "Ý nghĩa": "cư dân, người ở",
        "Cách nhớ nhanh": "In hạ bít tên – dân sống trong nơi nào đó"
    },
    {
        "Từ vựng": "initiate",
        "Phiên âm": "/ɪˈnɪʃieɪt/",
        "Loại từ": "n, v",
        "Ý nghĩa": "người nhập môn; bắt đầu",
        "Cách nhớ nhanh": "In như siêu nhẹ – bắt đầu làm"
    },
    {
        "Từ vựng": "innocent",
        "Phiên âm": "/ˈɪnəsnt/",
        "Loại từ": "adj",
        "Ý nghĩa": "ngây thơ, vô tội",
        "Cách nhớ nhanh": "In nó sợn – vô tội"
    },
    {
        "Từ vựng": "inroad",
        "Phiên âm": "/ˈɪnrəʊd/",
        "Loại từ": "n",
        "Ý nghĩa": "sự xâm nhập",
        "Cách nhớ nhanh": "In rồi đột nhập – inroad"
    },
    {
        "Từ vựng": "insight",
        "Phiên âm": "/ˈɪnsaɪt/",
        "Loại từ": "n",
        "Ý nghĩa": "sự hiểu biết sâu sắc",
        "Cách nhớ nhanh": "In sai rồi mới hiểu – insight"
    },
    {
        "Từ vựng": "insomnia",
        "Phiên âm": "/ɪnˈsɒmniə/",
        "Loại từ": "n",
        "Ý nghĩa": "chứng mất ngủ",
        "Cách nhớ nhanh": "In xong mê gì đâu – insomnia"
    },
    {
        "Từ vựng": "inspect",
        "Phiên âm": "/ɪnˈspekt/",
        "Loại từ": "v",
        "Ý nghĩa": "kiểm tra, thanh tra",
        "Cách nhớ nhanh": "In sách để kiểm – inspect"
    },
    {
        "Từ vựng": "instantly",
        "Phiên âm": "/ˈɪnstəntli/",
        "Loại từ": "adv",
        "Ý nghĩa": "ngay lập tức",
        "Cách nhớ nhanh": "Instant – liền, ngay"
    },
    {
        "Từ vựng": "instruction",
        "Phiên âm": "/ɪnˈstrʌkʃn/",
        "Loại từ": "n",
        "Ý nghĩa": "sự chỉ dẫn, lời hướng dẫn",
        "Cách nhớ nhanh": "In sách rắc chữ – instruction"
    },
    {
        "Từ vựng": "insufficient",
        "Phiên âm": "/ˌɪnsəˈfɪʃnt/",
        "Loại từ": "adj",
        "Ý nghĩa": "không đủ, thiếu thốn",
        "Cách nhớ nhanh": "In sơ phi sinh – không đủ giấy in sơ yếu lý lịch"
    },
    {
        "Từ vựng": "interesting",
        "Phiên âm": "/ˈɪntrəstɪŋ/",
        "Loại từ": "adj",
        "Ý nghĩa": "thú vị, gây chú ý",
        "Cách nhớ nhanh": "In trên tin – bài thú vị được in trên báo"
    },
    {
        "Từ vựng": "intolerant",
        "Phiên âm": "/ɪnˈtɒlərənt/",
        "Loại từ": "adj",
        "Ý nghĩa": "không dung thứ, không chịu được",
        "Cách nhớ nhanh": "In to là rằn – không chịu đựng tiếng rằn to"
    },
    {
        "Từ vựng": "intrude",
        "Phiên âm": "/ɪnˈtruːd/",
        "Loại từ": "v",
        "Ý nghĩa": "xâm nhập, xâm phạm",
        "Cách nhớ nhanh": "In trụt – xâm nhập rồi bị trượt té"
    },
    {
        "Từ vựng": "invade",
        "Phiên âm": "/ɪnˈveɪd/",
        "Loại từ": "v",
        "Ý nghĩa": "xâm lược, xâm chiếm",
        "Cách nhớ nhanh": "In về – quân xâm lược in cờ về"
    },
    {
        "Từ vựng": "inventory",
        "Phiên âm": "/ˈɪnvəntəri/",
        "Loại từ": "n",
        "Ý nghĩa": "sự kiểm kê, bản kiểm kê",
        "Cách nhớ nhanh": "In vở tờ ri – danh sách kiểm kê in trong vở"
    },
    {
        "Từ vựng": "investigate",
        "Phiên âm": "/ɪnˈvestɪɡeɪt/",
        "Loại từ": "v",
        "Ý nghĩa": "điều tra, nghiên cứu",
        "Cách nhớ nhanh": "In vé xì ghế – cảnh sát điều tra vé giả trong rạp"
    },
    {
        "Từ vựng": "invincible",
        "Phiên âm": "/ɪnˈvɪnsəbl/",
        "Loại từ": "adj",
        "Ý nghĩa": "vô địch, bất khả chiến bại",
        "Cách nhớ nhanh": "In vinh xử bồ – đội vô địch khiến ai cũng phục"
    }
]